__init__.py
schema_validator.py
utilities.py
pyspark_common_utilities-0.1.7.dist-info/METADATA
pyspark_common_utilities-0.1.7.dist-info/WHEEL
pyspark_common_utilities-0.1.7.dist-info/top_level.txt
pyspark_common_utilities-0.1.7.dist-info/RECORD
