Metadata-Version: 2.4
Name: pyspark_common_utilities
Version: 0.1.7
Summary: Reusable PySpark common utility functions for data pipelines
Author-email: Hakim Pocketwalla <hakim.pocketwalla@nearform.com>
License: MIT
Project-URL: Homepage, https://github.com/nearform/pyspark-common-utilities
Requires-Python: >=3.7
Requires-Dist: pyspark>=3.0.0
Provides-Extra: dev
Requires-Dist: pytest; extra == "dev"
Requires-Dist: flake8; extra == "dev"
Requires-Dist: mypy; extra == "dev"
Requires-Dist: ruff; extra == "dev"
